3o Período/Arquitetura de Computadores I/Guia 09/03/Guia_0903.v
/*
*   Ricardo Soares Cerqueira
*   803833
*/

module clock ( output clk );
    reg clk;
    initial begin
        clk = 1'b0;
    end
    always begin
        #12 clk = ~clk;
    end
endmodule // clock

module pulse ( signal, clock );
    input clock;
    output signal;      
    reg signal;
    always @ (posedge clock ) begin
        signal = 1'b1;
        #48 signal = 1'b0;
        #48 signal = 1'b1;
        #48 signal = 1'b0;
    end
endmodule // pulse

module Guia_0903;
    wire clock;
    clock clk ( clock );
    wire p;

    pulse pls( p, clock );

    initial begin
        $dumpfile ( "Guia_0903.vcd" );
        $dumpvars ( 1, clock, p);

        $display("\nGuia_0903 - Ricardo Soares Cerqueira - 803833\n");

        $monitor("clock = %b / p = %b ", clock, p);
        #1000 $finish;
    end
endmodule

3o Período/Arquitetura de Computadores I/Guia 09/03/Guia_0903.vcd
$date
	Sun Apr 14 12:17:31 2024
$end
$version
	Icarus Verilog
$end
$timescale
	1s
$end
$scope module Guia_0903 $end
$var wire 1 ! clock $end
$upscope $end
$scope module Guia_0903 $end
$var wire 1 " p $end
$upscope $end
$enddefinitions $end
#0
$dumpvars
x"
0!
$end
#12
1"
1!
#24
0!
#36
1!
#48
0!
#60
1!
0"
#72
0!
#84
1!
#96
0!
#108
1!
1"
#120
0!
#132
1!
#144
0!
#156
1!
1"
#168
0!
#180
1!
#192
0!
#204
1!
0"
#216
0!
#228
1!
#240
0!
#252
1!
1"
#264
0!
#276
1!
#288
0!
#300
1!
1"
#312
0!
#324
1!
#336
0!
#348
1!
0"
#360
0!
#372
1!
#384
0!
#396
1!
1"
#408
0!
#420
1!
#432
0!
#444
1!
1"
#456
0!
#468
1!
#480
0!
#492
1!
0"
#504
0!
#516
1!
#528
0!
#540
1!
1"
#552
0!
#564
1!
#576
0!
#588
1!
1"
#600
0!
#612
1!
#624
0!
#636
1!
0"
#648
0!
#660
1!
#672
0!
#684
1!
1"
#696
0!
#708
1!
#720
0!
#732
1!
1"
#744
0!
#756
1!
#768
0!
#780
1!
0"
#792
0!
#804
1!
#816
0!
#828
1!
1"
#840
0!
#852
1!
#864
0!
#876
1!
1"
#888
0!
#900
1!
#912
0!
#924
1!
0"
#936
0!
#948
1!
#960
0!
#972
1!
1"
