3o Período/Arquitetura de Computadores I/Guia 09/04/Guia_0904.v
/*
*   Ricardo Soares Cerqueira
*   803833
*/

module clock ( output clk );
    reg clk;
    initial begin
        clk = 1'b0;
    end
    always begin
        #12 clk = ~clk;
    end
endmodule // clock

module pulse1 (signal, clock);
    input clock;
    output signal;      
    reg signal;

    always @ (posedge clock ) begin;
        signal = 1'b1;
        #4 signal = 1'b0;
        #4 signal = 1'b1;
        #4 signal = 1'b0;
        #4 signal = 1'b1;
        #4 signal = 1'b0;    
    end
endmodule // pulse1

module Guia_0904;
    wire clock;
    wire p;
    
    clock clk (clock);
    pulse1 pls(p, clock);

    initial begin
        $dumpfile("Guia_0904.vcd");
        $dumpvars(0, Guia_0904);

        $display("\nGuia_0902 - Ricardo Soares Cerqueira - 803833\n");

        $monitor("clock = %b / p = %b ", clock, p);
        #1000 $finish;
    end
endmodule // Guia_0904

3o Período/Arquitetura de Computadores I/Guia 09/04/Guia_0904.vcd
$date
	Sun Apr 14 12:19:37 2024
$end
$version
	Icarus Verilog
$end
$timescale
	1s
$end
$scope module Guia_0904 $end
$var wire 1 ! p $end
$var wire 1 " clock $end
$scope module clk $end
$var reg 1 " clk $end
$upscope $end
$scope module pls $end
$var wire 1 " clock $end
$var reg 1 ! signal $end
$upscope $end
$upscope $end
$enddefinitions $end
#0
$dumpvars
0"
x!
$end
#12
1!
1"
#16
0!
#20
1!
#24
0!
0"
#28
1!
#32
0!
#36
1!
1"
#40
0!
#44
1!
#48
0!
0"
#52
1!
#56
0!
#60
1!
1"
#64
0!
#68
1!
#72
0!
0"
#76
1!
#80
0!
#84
1!
1"
#88
0!
#92
1!
#96
0!
0"
#100
1!
#104
0!
#108
1!
1"
#112
0!
#116
1!
#120
0!
0"
#124
1!
#128
0!
#132
1!
1"
#136
0!
#140
1!
#144
0!
0"
#148
1!
#152
0!
#156
1!
1"
#160
0!
#164
1!
#168
0!
0"
#172
1!
#176
0!
#180
1!
1"
#184
0!
#188
1!
#192
0!
0"
#196
1!
#200
0!
#204
1!
1"
#208
0!
#212
1!
#216
0!
0"
#220
1!
#224
0!
#228
1!
1"
#232
0!
#236
1!
#240
0!
0"
#244
1!
#248
0!
#252
1!
1"
#256
0!
#260
1!
#264
0!
0"
#268
1!
#272
0!
#276
1!
1"
#280
0!
#284
1!
#288
0!
0"
#292
1!
#296
0!
#300
1!
1"
#304
0!
#308
1!
#312
0!
0"
#316
1!
#320
0!
#324
1!
1"
#328
0!
#332
1!
#336
0!
0"
#340
1!
#344
0!
#348
1!
1"
#352
0!
#356
1!
#360
0!
0"
#364
1!
#368
0!
#372
1!
1"
#376
0!
#380
1!
#384
0!
0"
#388
1!
#392
0!
#396
1!
1"
#400
0!
#404
1!
#408
0!
0"
#412
1!
#416
0!
#420
1!
1"
#424
0!
#428
1!
#432
0!
0"
#436
1!
#440
0!
#444
1!
1"
#448
0!
#452
1!
#456
0!
0"
#460
1!
#464
0!
#468
1!
1"
#472
0!
#476
1!
#480
0!
0"
#484
1!
#488
0!
#492
1!
1"
#496
0!
#500
1!
#504
0!
0"
#508
1!
#512
0!
#516
1!
1"
#520
0!
#524
1!
#528
0!
0"
#532
1!
#536
0!
#540
1!
1"
#544
0!
#548
1!
#552
0!
0"
#556
1!
#560
0!
#564
1!
1"
#568
0!
#572
1!
#576
0!
0"
#580
1!
#584
0!
#588
1!
1"
#592
0!
#596
1!
#600
0!
0"
#604
1!
#608
0!
#612
1!
1"
#616
0!
#620
1!
#624
0!
0"
#628
1!
#632
0!
#636
1!
1"
#640
0!
#644
1!
#648
0!
0"
#652
1!
#656
0!
#660
1!
1"
#664
0!
#668
1!
#672
0!
0"
#676
1!
#680
0!
#684
1!
1"
#688
0!
#692
1!
#696
0!
0"
#700
1!
#704
0!
#708
1!
1"
#712
0!
#716
1!
#720
0!
0"
#724
1!
#728
0!
#732
1!
1"
#736
0!
#740
1!
#744
0!
0"
#748
1!
#752
0!
#756
1!
1"
#760
0!
#764
1!
#768
0!
0"
#772
1!
#776
0!
#780
1!
1"
#784
0!
#788
1!
#792
0!
0"
#796
1!
#800
0!
#804
1!
1"
#808
0!
#812
1!
#816
0!
0"
#820
1!
#824
0!
#828
1!
1"
#832
0!
#836
1!
#840
0!
0"
#844
1!
#848
0!
#852
1!
1"
#856
0!
#860
1!
#864
0!
0"
#868
1!
#872
0!
#876
1!
1"
#880
0!
#884
1!
#888
0!
0"
#892
1!
#896
0!
#900
1!
1"
#904
0!
#908
1!
#912
0!
0"
#916
1!
#920
0!
#924
1!
1"
#928
0!
#932
1!
#936
0!
0"
#940
1!
#944
0!
#948
1!
1"
#952
0!
#956
1!
#960
0!
0"
#964
1!
#968
0!
#972
1!
1"
#976
0!
#980
1!
#984
0!
0"
#988
1!
#992
0!
#996
1!
1"
#1000
0!
