3o Período/Arquitetura de Computadores I/Guia 09/02/Guia_0902.v
/*
*   Ricardo Soares Cerqueira
*   803833
*/

module clock ( output clk );
    reg clk;
    initial begin
        clk = 1'b0;
    end
    always begin
        #12 clk = ~clk;
    end
endmodule

module pulse1 ( signal, clock );
    input clock;
    output signal;
    reg signal;
    
    always @ ( posedge clock ) begin
        signal = 1'b1;
        #4 signal = 1'b0;
        #4 signal = 1'b1;
        #4 signal = 1'b0;
        #4 signal = 1'b1;
        #4 signal = 1'b0;
    end
endmodule // pulse

module pulse2 ( signal, clock );
    input clock;
    output signal;
    reg signal;

    always @ ( posedge clock ) begin
        signal = 1'b1;  
        #5 signal = 1'b0;
    end
endmodule // pulse

module pulse3 ( signal, clock );
    input clock;
    output signal;
    reg signal;

    always @ ( negedge clock ) begin
        signal = 1'b1;
        #15 signal = 1'b0;
        #15 signal = 1'b1;
    end
endmodule // pulse

module pulse4 ( signal, clock );
    input clock;
    output signal;
    reg signal;

    always @ ( negedge clock ) begin
        signal = 1'b1;
        #20 signal = 1'b0;
        #20 signal = 1'b1;
        #20 signal = 1'b0;  
    end
endmodule // pulse

module Guia_0902;
    wire clock;
    clock clk ( clock );
    wire p1,p2,p3,p4;

    pulse1 pls1( p1, clock );
    pulse2 pls2( p2, clock );
    pulse3 pls3( p3, clock );
    pulse4 pls4( p4, clock );

    initial begin
        $dumpfile ( "Guia_0902.vcd" );
        $dumpvars ( 1, clock, p1, p2, p3, p4 ); 

        $display("\nGuia_0902 - Ricardo Soares Cerqueira - 803833\n");

        $monitor("clock = %b | p1 = %b | p2 = %b | p3 = %b | p4 = %b", clock, p1, p2, p3, p4);
        #1000 $finish;
    end
endmodule // Guia_0902

3o Período/Arquitetura de Computadores I/Guia 09/02/Guia_0902.vcd
$date
	Sun Apr 14 12:10:19 2024
$end
$version
	Icarus Verilog
$end
$timescale
	1s
$end
$scope module Guia_0902 $end
$var wire 1 ! clock $end
$upscope $end
$scope module Guia_0902 $end
$var wire 1 " p1 $end
$upscope $end
$scope module Guia_0902 $end
$var wire 1 # p2 $end
$upscope $end
$scope module Guia_0902 $end
$var wire 1 $ p3 $end
$upscope $end
$scope module Guia_0902 $end
$var wire 1 % p4 $end
$upscope $end
$enddefinitions $end
#0
$dumpvars
x%
x$
x#
x"
0!
$end
#12
1"
1#
1!
#16
0"
#17
0#
#20
1"
#24
1$
1%
0"
0!
#28
1"
#32
0"
#36
1#
1"
1!
#39
0$
#40
0"
#41
0#
#44
1"
0%
#48
0"
0!
#52
1"
#54
1$
#56
0"
#60
1#
1"
1!
#64
0"
1%
#65
0#
#68
1"
#72
0"
0!
#76
1"
#80
0"
#84
1#
1"
1!
0%
#87
0$
#88
0"
#89
0#
#92
1"
#96
1%
0"
0!
#100
1"
#102
1$
#104
0"
#108
1#
1"
1!
#112
0"
#113
0#
#116
1"
0%
#120
0"
0!
#124
1"
#128
0"
#132
1#
1"
1!
#135
0$
#136
0"
1%
#137
0#
#140
1"
#144
0"
0!
#148
1"
#150
1$
#152
0"
#156
1#
1"
1!
0%
#160
0"
#161
0#
#164
1"
#168
1%
0"
0!
#172
1"
#176
0"
#180
1#
1"
1!
#183
0$
#184
0"
#185
0#
#188
1"
0%
#192
0"
0!
#196
1"
#198
1$
#200
0"
#204
1#
1"
1!
#208
0"
1%
#209
0#
#212
1"
#216
0"
0!
#220
1"
#224
0"
#228
1#
1"
1!
0%
#231
0$
#232
0"
#233
0#
#236
1"
#240
1%
0"
0!
#244
1"
#246
1$
#248
0"
#252
1#
1"
1!
#256
0"
#257
0#
#260
1"
0%
#264
0"
0!
#268
1"
#272
0"
#276
1#
1"
1!
#279
0$
#280
0"
1%
#281
0#
#284
1"
#288
0"
0!
#292
1"
#294
1$
#296
0"
#300
1#
1"
1!
0%
#304
0"
#305
0#
#308
1"
#312
1%
0"
0!
#316
1"
#320
0"
#324
1#
1"
1!
#327
0$
#328
0"
#329
0#
#332
1"
0%
#336
0"
0!
#340
1"
#342
1$
#344
0"
#348
1#
1"
1!
#352
0"
1%
#353
0#
#356
1"
#360
0"
0!
#364
1"
#368
0"
#372
1#
1"
1!
0%
#375
0$
#376
0"
#377
0#
#380
1"
#384
1%
0"
0!
#388
1"
#390
1$
#392
0"
#396
1#
1"
1!
#400
0"
#401
0#
#404
1"
0%
#408
0"
0!
#412
1"
#416
0"
#420
1#
1"
1!
#423
0$
#424
0"
1%
#425
0#
#428
1"
#432
0"
0!
#436
1"
#438
1$
#440
0"
#444
1#
1"
1!
0%
#448
0"
#449
0#
#452
1"
#456
1%
0"
0!
#460
1"
#464
0"
#468
1#
1"
1!
#471
0$
#472
0"
#473
0#
#476
1"
0%
#480
0"
0!
#484
1"
#486
1$
#488
0"
#492
1#
1"
1!
#496
0"
1%
#497
0#
#500
1"
#504
0"
0!
#508
1"
#512
0"
#516
1#
1"
1!
0%
#519
0$
#520
0"
#521
0#
#524
1"
#528
1%
0"
0!
#532
1"
#534
1$
#536
0"
#540
1#
1"
1!
#544
0"
#545
0#
#548
1"
0%
#552
0"
0!
#556
1"
#560
0"
#564
1#
1"
1!
#567
0$
#568
0"
1%
#569
0#
#572
1"
#576
0"
0!
#580
1"
#582
1$
#584
0"
#588
1#
1"
1!
0%
#592
0"
#593
0#
#596
1"
#600
1%
0"
0!
#604
1"
#608
0"
#612
1#
1"
1!
#615
0$
#616
0"
#617
0#
#620
1"
0%
#624
0"
0!
#628
1"
#630
1$
#632
0"
#636
1#
1"
1!
#640
0"
1%
#641
0#
#644
1"
#648
0"
0!
#652
1"
#656
0"
#660
1#
1"
1!
0%
#663
0$
#664
0"
#665
0#
#668
1"
#672
1%
0"
0!
#676
1"
#678
1$
#680
0"
#684
1#
1"
1!
#688
0"
#689
0#
#692
1"
0%
#696
0"
0!
#700
1"
#704
0"
#708
1#
1"
1!
#711
0$
#712
0"
1%
#713
0#
#716
1"
#720
0"
0!
#724
1"
#726
1$
#728
0"
#732
1#
1"
1!
0%
#736
0"
#737
0#
#740
1"
#744
1%
0"
0!
#748
1"
#752
0"
#756
1#
1"
1!
#759
0$
#760
0"
#761
0#
#764
1"
0%
#768
0"
0!
#772
1"
#774
1$
#776
0"
#780
1#
1"
1!
#784
0"
1%
#785
0#
#788
1"
#792
0"
0!
#796
1"
#800
0"
#804
1#
1"
1!
0%
#807
0$
#808
0"
#809
0#
#812
1"
#816
1%
0"
0!
#820
1"
#822
1$
#824
0"
#828
1#
1"
1!
#832
0"
#833
0#
#836
1"
0%
#840
0"
0!
#844
1"
#848
0"
#852
1#
1"
1!
#855
0$
#856
0"
1%
#857
0#
#860
1"
#864
0"
0!
#868
1"
#870
1$
#872
0"
#876
1#
1"
1!
0%
#880
0"
#881
0#
#884
1"
#888
1%
0"
0!
#892
1"
#896
0"
#900
1#
1"
1!
#903
0$
#904
0"
#905
0#
#908
1"
0%
#912
0"
0!
#916
1"
#918
1$
#920
0"
#924
1#
1"
1!
#928
0"
1%
#929
0#
#932
1"
#936
0"
0!
#940
1"
#944
0"
#948
1#
1"
1!
0%
#951
0$
#952
0"
#953
0#
#956
1"
#960
1%
0"
0!
#964
1"
#966
1$
#968
0"
#972
1#
1"
1!
#976
0"
#977
0#
#980
1"
0%
#984
0"
0!
#988
1"
#992
0"
#996
1#
1"
1!
#999
0$
#1000
0"
1%
